owl_energy-0.0.3.dist-info/DESCRIPTION.rst
owl_energy-0.0.3.dist-info/METADATA
owl_energy-0.0.3.dist-info/RECORD
owl_energy-0.0.3.dist-info/WHEEL
owl_energy-0.0.3.dist-info/metadata.json
owl_energy-0.0.3.dist-info/top_level.txt
owlenergy/__init__.py
owlenergy/client.py
owlenergy/owl.py
