Metadata-Version: 2.0
Name: owl-energy
Version: 0.0.3
Summary: A python package for OWL energy monitor using sockets
Home-page: https://stretchproject.org
Author: Ciaran McCormick
Author-email: ciaran.mccormick@open.ac.uk
License: MIT
Keywords: owl energy monitor consumption current
Platform: UNKNOWN
